cpm/__init__.py
cpm/__version__.py
cpm/cpm.py
cpm/applications/__init__.py
cpm/applications/decision_making.py
cpm/applications/reinforcement_learning.py
cpm/applications/signal_detection.py
cpm/core/__init__.py
cpm/core/data.py
cpm/core/diagnostics.py
cpm/core/exports.py
cpm/core/generators.py
cpm/core/optimisers.py
cpm/core/parallel.py
cpm/datasets/__init__.py
cpm/datasets/base.py
cpm/datasets/data/__init__.py
cpm/datasets/data/bandit_small.csv
cpm/datasets/data/risky_choices.csv
cpm/generators/__init__.py
cpm/generators/parameters.py
cpm/generators/simulator.py
cpm/generators/wrapper.py
cpm/hierarchical/__init__.py
cpm/hierarchical/empirical.py
cpm/hierarchical/variational.py
cpm/models/__init__.py
cpm/models/activation.py
cpm/models/decision.py
cpm/models/learning.py
cpm/models/utils.py
cpm/optimisation/__init__.py
cpm/optimisation/bads.py
cpm/optimisation/fmin.py
cpm/optimisation/free.py
cpm/optimisation/genetic.py
cpm/optimisation/minimise.py
cpm/utils/__init__.py
cpm/utils/data.py
cpm/utils/metad.py
cpm_toolbox-0.23.18.dist-info/licenses/LICENSE
cpm_toolbox-0.23.18.dist-info/licenses/LICENSES-BUNDLE
docs/examples/fitting-hierarchical-run.py
docs/examples/model-recovery-run.py
docs/examples/functions/__init__.py
docs/examples/functions/model_anti.py
docs/examples/functions/model_delta.py
docs/examples/functions/model_kernel.py
site/examples/fitting-hierarchical-run/fitting-hierarchical-run.py
site/examples/functions/__init__/__init__.py
site/examples/functions/model_anti/model_anti.py
site/examples/functions/model_delta/model_delta.py
site/examples/functions/model_kernel/model_kernel.py
site/examples/model-recovery-run/model-recovery-run.py
test/__init__.py
test/test_cpm.py
test/applications/test_decision_making.py
test/applications/test_reinforcement_learning.py
test/applications/test_signal_detection.py
test/datasets/test_datasets.py
test/generators/test_parameters.py
test/generators/test_simulator.py
test/generators/test_wrapper.py
test/models/test_activation.py
test/models/test_decision.py
test/models/test_learning.py
test/models/test_utils.py
cpm_toolbox-0.23.18.dist-info/METADATA
cpm_toolbox-0.23.18.dist-info/WHEEL
cpm_toolbox-0.23.18.dist-info/top_level.txt
cpm_toolbox-0.23.18.dist-info/RECORD
