Metadata-Version: 2.4
Name: cpm-toolbox
Version: 0.23.18
Summary: A fundamental scientific toolbox for computational psychiatry and psychology.
Author: Lenard Dome, Frank Hezemans, Ben J. Wagner, Andrew Webb, Marc Carrera, Tobias Hauser
Maintainer-email: Lenard Dome <lenarddome@gmail.com>
License: AGPLv3
Project-URL: Homepage, https://cpm-toolbox.net
Project-URL: Documentation, https://devcompsy.github.io/cpm/
Keywords: cpm-toolbox,cpm,computational-psychiatry,computational-psychology,psychometrics,psychology
Classifier: Development Status :: 4 - Beta
Classifier: Intended Audience :: Developers
Classifier: License :: OSI Approved :: GNU Affero General Public License v3
Classifier: Natural Language :: English
Classifier: Programming Language :: Python :: 3
Classifier: Programming Language :: Python :: Implementation :: PyPy
Requires-Python: >3.11.0
License-File: LICENSE
License-File: LICENSES-BUNDLE
Requires-Dist: numpy>=2.0.0
Requires-Dist: SciPy>=1.16.0
Requires-Dist: pandas>=2.1.4
Requires-Dist: multiprocess>=0.70.16
Requires-Dist: ipyparallel>=8.8.0
Requires-Dist: numdifftools>=0.9.41
Requires-Dist: pybads>=1.0.4
Requires-Dist: dill>=0.3.8
Dynamic: license-file
